{
    "type": "minecraft:crafting_shaped",
    "pattern": [
        "#Oo",
        "FAH",
        "CWZ"
    ],
    "key": {
        "#": {
            "item": "oredium:disprosio_ingot"
        },
        "O": {
            "item": "oredium:miguelitio_ingot"
        },
        "o": {
            "item": "oredium:alezarita_ingot"
        },
        "F": {
            "item": "oredium:terium_ingot"
        },
        "A": {
            "item": "oredium:umc"
        },
        "H": {
            "item": "oredium:terium_ingot"
        },
        "C": {
            "item": "oredium:franitolina_ingot"
        },
        "W": {
            "item": "oredium:halinox_ingot"
        },
        "Z": {
            "item": "oredium:melitonila_ingot"
        }
    },
    "result": {
        "item": "oredium:oredium_amulet",
        "count": 1
    }
}